{"version":"3.8.0","examples":[{"id":"./spec/controllers/categories_controller_spec.rb[1:1:1]","description":"returns http success","full_description":"CategoriesController GET #show returns http success","status":"passed","file_path":"./spec/controllers/categories_controller_spec.rb","line_number":6,"run_time":0.073985724,"pending_message":null},{"id":"./spec/features/post_spec.rb[1:1]","description":"shows the title on the show page in a h1 tag","full_description":"navigate shows the title on the show page in a h1 tag","status":"passed","file_path":"./spec/features/post_spec.rb","line_number":8,"run_time":0.819107622,"pending_message":null},{"id":"./spec/features/post_spec.rb[1:2]","description":"to post pages","full_description":"navigate to post pages","status":"passed","file_path":"./spec/features/post_spec.rb","line_number":13,"run_time":0.012263853,"pending_message":null},{"id":"./spec/features/post_spec.rb[1:3]","description":"shows the description on the show page in a p tag","full_description":"navigate shows the description on the show page in a p tag","status":"passed","file_path":"./spec/features/post_spec.rb","line_number":18,"run_time":0.008623181,"pending_message":null},{"id":"./spec/features/post_spec.rb[2:1]","description":"shows an update form that submits content and redirects and prints out params","full_description":"form shows an update form that submits content and redirects and prints out params","status":"passed","file_path":"./spec/features/post_spec.rb","line_number":26,"run_time":0.055384783,"pending_message":null},{"id":"./spec/features/post_spec.rb[3:1]","description":"has a post_status field","full_description":"post has a post_status field","status":"passed","file_path":"./spec/features/post_spec.rb","line_number":41,"run_time":0.006903845,"pending_message":null},{"id":"./spec/helpers/accounts_helper_spec.rb[1:1]","description":"add some examples to (or delete) /home/ellefaraday/rails-generators-readme-v-000/spec/helpers/accounts_helper_spec.rb","full_description":"AccountsHelper add some examples to (or delete) /home/ellefaraday/rails-generators-readme-v-000/spec/helpers/accounts_helper_spec.rb","status":"pending","file_path":"./spec/helpers/accounts_helper_spec.rb","line_number":14,"run_time":1.3121e-05,"pending_message":"Not yet implemented"},{"id":"./spec/models/account_spec.rb[1:1]","description":"add some examples to (or delete) /home/ellefaraday/rails-generators-readme-v-000/spec/models/account_spec.rb","full_description":"Account add some examples to (or delete) /home/ellefaraday/rails-generators-readme-v-000/spec/models/account_spec.rb","status":"pending","file_path":"./spec/models/account_spec.rb","line_number":4,"run_time":6.168e-06,"pending_message":"Not yet implemented"},{"id":"./spec/models/author_spec.rb[1:1]","description":"has a name","full_description":"Author has a name","status":"passed","file_path":"./spec/models/author_spec.rb","line_number":4,"run_time":0.011701152,"pending_message":null},{"id":"./spec/models/author_spec.rb[1:2]","description":"has a genre","full_description":"Author has a genre","status":"passed","file_path":"./spec/models/author_spec.rb","line_number":10,"run_time":0.001764406,"pending_message":null},{"id":"./spec/models/author_spec.rb[1:3]","description":"has a bio","full_description":"Author has a bio","status":"passed","file_path":"./spec/models/author_spec.rb","line_number":16,"run_time":0.001797029,"pending_message":null},{"id":"./spec/models/category_spec.rb[1:1:1]","description":"has many posts","full_description":"Category relations has many posts","status":"passed","file_path":"./spec/models/category_spec.rb","line_number":5,"run_time":0.013914667,"pending_message":null}],"summary":{"duration":1.162934954,"example_count":12,"failure_count":0,"pending_count":2,"errors_outside_of_examples_count":0},"summary_line":"12 examples, 0 failures, 2 pending"}